{
   "columns" : 640,
   "count" : 4,
   "manufacturer" : "ALOKA CO., LTD.",
   "model name" : "SSD-ALPHA5",
   "rows" : 480,
   "shapes" : [
      {
         "count" : 4,
         "points" : [
            [ 69, 21 ],
            [ 69, 0 ],
            [ 643, 0 ],
            [ 643, 21 ]
         ]
      },
      {
         "count" : 4,
         "points" : [
            [ 15, 448 ],
            [ 15, 472 ],
            [ 634, 472 ],
            [ 634, 448 ]
         ]
      },
      {
         "count" : 4,
         "points" : [
            [ 142, 131 ],
            [ 142, 186 ],
            [ 195, 186 ],
            [ 195, 131 ]
         ]
      },
      {
         "count" : 4,
         "points" : [
            [ 182, 254 ],
            [ 182, 310 ],
            [ 313, 309 ],
            [ 307, 254 ]
         ]
      }
   ]
}
